setup.py
setvar/__init__.py
setvar.egg-info/PKG-INFO
setvar.egg-info/SOURCES.txt
setvar.egg-info/dependency_links.txt
setvar.egg-info/top_level.txt