Metadata-Version: 1.0
Name: setvar
Version: 1.1.2
Summary: Provide a bash-like method of setting environment vars
Home-page: http://cct.lsu.edu/~sbrandt/
Author: Steven R. Brandt
Author-email: sbrandt@cct.lsu.edu
License: LGPL
Platform: UNKNOWN
